layerborn/cdk_ami_builder/__init__.py
layerborn/cdk_ami_builder/py.typed
layerborn/cdk_ami_builder/_jsii/__init__.py
layerborn/cdk_ami_builder/_jsii/cdk-ami-builder@0.0.6.jsii.tgz
layerborn.cdk_ami_builder-0.0.6.dist-info/LICENSE
layerborn.cdk_ami_builder-0.0.6.dist-info/METADATA
layerborn.cdk_ami_builder-0.0.6.dist-info/WHEEL
layerborn.cdk_ami_builder-0.0.6.dist-info/top_level.txt
layerborn.cdk_ami_builder-0.0.6.dist-info/RECORD
