Metadata-Version: 2.1
Name: layerborn.cdk-ami-builder
Version: 0.0.6
Summary: Creates an EC2 AMI using an Image Builder Pipeline and returns the AMI ID.
Home-page: https://github.com/layerborn/cdk-ami-builder-construct.git
Author: Jayson Rawlins<jayson.rawlins@layerborn.io>
License: Apache-2.0
Project-URL: Source, https://github.com/layerborn/cdk-ami-builder-construct.git
Classifier: Intended Audience :: Developers
Classifier: Operating System :: OS Independent
Classifier: Programming Language :: JavaScript
Classifier: Programming Language :: Python :: 3 :: Only
Classifier: Programming Language :: Python :: 3.8
Classifier: Programming Language :: Python :: 3.9
Classifier: Programming Language :: Python :: 3.10
Classifier: Programming Language :: Python :: 3.11
Classifier: Typing :: Typed
Classifier: Development Status :: 5 - Production/Stable
Classifier: License :: OSI Approved
Requires-Python: ~=3.8
License-File: LICENSE
Requires-Dist: aws-cdk-lib <3.0.0,>=2.100.0
Requires-Dist: constructs <11.0.0,>=10.3.0
Requires-Dist: jsii <2.0.0,>=1.98.0
Requires-Dist: layerborn.cdk-iam-policy-builder-helper <0.0.5,>=0.0.4
Requires-Dist: publication >=0.0.3
Requires-Dist: typeguard ~=2.13.3
